appstract/__init__.py
appstract/protocols.py
appstract/py.typed
appstract/schedulers.py
appstract/constructors/__init__.py
appstract/constructors/_test_helpers.py
appstract/constructors/factories.py
appstract/constructors/inspectors.py
appstract/constructors/providers.py
appstract/logging/__init__.py
appstract/logging/_test_helpers.py
appstract/logging/formatters.py
appstract/logging/handlers.py
appstract/logging/providers.py
appstract/logging/resources.py
appstract-24.12.0.dist-info/LICENSE
appstract-24.12.0.dist-info/METADATA
appstract-24.12.0.dist-info/WHEEL
appstract-24.12.0.dist-info/top_level.txt
appstract-24.12.0.dist-info/RECORD
